pyhapi/__init__.py
pyhapi/conf.py
pyhapi/hapi.py
pyhapi/hasset.py
pyhapi/hdata.py
pyhapi/hgeo.py
pyhapi/hnode.py
pyhapi/hparm.py
pyhapi/hsession.py
pyhapi/sethoupath.ps1
pyhapi-0.0.4b2.dist-info/LICENSE
pyhapi-0.0.4b2.dist-info/METADATA
pyhapi-0.0.4b2.dist-info/WHEEL
pyhapi-0.0.4b2.dist-info/top_level.txt
pyhapi-0.0.4b2.dist-info/RECORD
