Metadata-Version: 2.1
Name: pyhapi
Version: 0.0.4b2
Summary: A object-oriented python wrapper for houdini engine's C API
Home-page: https://github.com/maajor/pyhapi
Author: Yidong Ma(Maajor)
Author-email: info@ma-yidong.com
Maintainer: Yidong Ma(Maajor)
Maintainer-email: info@ma-yidong.com
License: MIT
Project-URL: Documentation, https://pyhapi.readthedocs.io
Project-URL: Code, https://github.com/maajor/pyhapi
Project-URL: Issue tracker, https://github.com/maajor/pyhapi/issues
Platform: UNKNOWN
Classifier: Development Status :: 2 - Pre-Alpha
Classifier: Environment :: Console
Classifier: Intended Audience :: Developers
Classifier: License :: OSI Approved :: MIT License
Classifier: Operating System :: OS Independent
Classifier: Programming Language :: Python
Classifier: Programming Language :: Python :: 3
Classifier: Programming Language :: Python :: 3.6
Classifier: Programming Language :: Python :: 3.7
Classifier: Topic :: Multimedia
Classifier: Topic :: Software Development :: Libraries :: Python Modules
Requires-Python: >=3.6
Requires-Dist: numpy (>=1.15.0)
